LICENSE
MANIFEST.in
README.rst
setup.py
pybuilder_django_enhanced_plugin/__init__.py
pybuilder_django_enhanced_plugin/external_command.py
pybuilder_django_enhanced_plugin/init.py
pybuilder_django_enhanced_plugin.egg-info/PKG-INFO
pybuilder_django_enhanced_plugin.egg-info/SOURCES.txt
pybuilder_django_enhanced_plugin.egg-info/dependency_links.txt
pybuilder_django_enhanced_plugin.egg-info/entry_points.txt
pybuilder_django_enhanced_plugin.egg-info/requires.txt
pybuilder_django_enhanced_plugin.egg-info/top_level.txt
pybuilder_django_enhanced_plugin.egg-info/zip-safe
pybuilder_django_enhanced_plugin/tasks/__init__.py
pybuilder_django_enhanced_plugin/tasks/common.py
pybuilder_django_enhanced_plugin/tasks/django_coverage.py
pybuilder_django_enhanced_plugin/tasks/django_generate.py
pybuilder_django_enhanced_plugin/tasks/django_migrations.py
pybuilder_django_enhanced_plugin/tasks/django_syncdb.py
pybuilder_django_enhanced_plugin/tasks/django_test.py
pybuilder_django_enhanced_plugin/tasks/e2e_testserver.py
pybuilder_django_enhanced_plugin/tasks/management_commands.py
pybuilder_django_enhanced_plugin/tasks/runserver.py